aesencrypter.py
aesencrypter-1.6.dist-info/METADATA
aesencrypter-1.6.dist-info/WHEEL
aesencrypter-1.6.dist-info/top_level.txt
aesencrypter-1.6.dist-info/RECORD
