Metadata-Version: 2.1
Name: aesencrypter
Version: 1.6
Summary: AES-256 CBC Encrypt/Decrypt utility package
Home-page: http://www.solucionesandinas.com.ar
Author: Soluciones Andinas
Author-email: info@sandinas.com.ar
License: UNKNOWN
Platform: UNKNOWN
Classifier: Programming Language :: Python :: 3.7
Classifier: Operating System :: OS Independent
Requires-Dist: pycryptodome
Requires-Dist: pycryptodomex
